assets/ESA_logo.svg
assets/__init__.py
cutana/__init__.py
cutana/catalogue_preprocessor.py
cutana/catalogue_streamer.py
cutana/constants.py
cutana/cutout_extraction.py
cutana/cutout_process.py
cutana/cutout_process_utils.py
cutana/cutout_writer_fits.py
cutana/cutout_writer_zarr.py
cutana/deployment_validator.py
cutana/fits_dataset.py
cutana/fits_reader.py
cutana/flux_conversion.py
cutana/get_default_config.py
cutana/image_processor.py
cutana/job_tracker.py
cutana/loadbalancer.py
cutana/logging_config.py
cutana/normalisation_parameters.py
cutana/orchestrator.py
cutana/performance_profiler.py
cutana/preview_generator.py
cutana/process_status_reader.py
cutana/process_status_writer.py
cutana/progress_report.py
cutana/streaming_orchestrator.py
cutana/system_monitor.py
cutana/validate_config.py
cutana-0.2.1.dist-info/licenses/LICENCE.txt
cutana_ui/README.md
cutana_ui/__init__.py
cutana_ui/app.py
cutana_ui/styles.py
cutana_ui/main_screen/__init__.py
cutana_ui/main_screen/configuration_panel.py
cutana_ui/main_screen/main_screen.py
cutana_ui/main_screen/preview_panel.py
cutana_ui/main_screen/status_panel.py
cutana_ui/start_screen/__init__.py
cutana_ui/start_screen/configuration_component.py
cutana_ui/start_screen/file_selection.py
cutana_ui/start_screen/output_folder.py
cutana_ui/start_screen/start_screen.py
cutana_ui/utils/__init__.py
cutana_ui/utils/backend_interface.py
cutana_ui/utils/log_manager.py
cutana_ui/utils/markdown_loader.py
cutana_ui/utils/svg_loader.py
cutana_ui/widgets/__init__.py
cutana_ui/widgets/configuration_widget.py
cutana_ui/widgets/file_chooser.py
cutana_ui/widgets/header_version_help.py
cutana_ui/widgets/loading_spinner.py
cutana_ui/widgets/normalisation_config_widget.py
cutana_ui/widgets/progress_bar.py
cutana-0.2.1.dist-info/METADATA
cutana-0.2.1.dist-info/WHEEL
cutana-0.2.1.dist-info/top_level.txt
cutana-0.2.1.dist-info/RECORD
