Metadata-Version: 2.4
Name: cutana
Version: 0.2.1
Summary: High-performance Python tool for creating astronomical image cutouts
Author-email: European Space Agency <pablo.gomez@esa.int>
Project-URL: Homepage, https://github.com/ESA-Datalabs/cutana
Project-URL: Repository, https://github.com/ESA-Datalabs/cutana
Project-URL: Issues, https://github.com/ESA-Datalabs/cutana/issues
Classifier: Development Status :: 3 - Alpha
Classifier: Intended Audience :: Science/Research
Classifier: Programming Language :: Python :: 3
Classifier: Programming Language :: Python :: 3.10
Classifier: Topic :: Scientific/Engineering :: Astronomy
Requires-Python: <3.14,>=3.10
License-File: LICENCE.txt
Requires-Dist: astropy>=5.0
Requires-Dist: dotmap>=1.3
Requires-Dist: drizzle>=2.0.1
Requires-Dist: fitsbolt>=0.1.6
Requires-Dist: fsspec>=2023.1.0
Requires-Dist: images-to-zarr>=0.3.5
Requires-Dist: ipyfilechooser>=0.6
Requires-Dist: ipykernel<7,>=6.29
Requires-Dist: ipywidgets>=8.0
Requires-Dist: loguru>=0.6
Requires-Dist: matplotlib>=3.5
Requires-Dist: numpy>=1.20
Requires-Dist: pandas>=1.3
Requires-Dist: portalocker>=2.0
Requires-Dist: psutil>=5.8
Requires-Dist: pyarrow>=14.0.0
Requires-Dist: scikit-image>=0.21
Requires-Dist: toml>=0.10
Provides-Extra: ui
Requires-Dist: voila; extra == "ui"
Provides-Extra: dev
Requires-Dist: pytest>=7.0; extra == "dev"
Requires-Dist: pytest-cov>=4.0; extra == "dev"
Requires-Dist: pytest-mock>=3.0; extra == "dev"
Requires-Dist: pytest-asyncio>=0.21; extra == "dev"
Requires-Dist: black>=22.0; extra == "dev"
Requires-Dist: flake8>=5.0; extra == "dev"
Requires-Dist: vulture>=2.10; extra == "dev"
Requires-Dist: playwright>=1.40; extra == "dev"
Requires-Dist: pytest-playwright>=0.4; extra == "dev"
Provides-Extra: all
Requires-Dist: cutana[dev,ui]; extra == "all"
Dynamic: license-file
